mandsot/__init__.py
mandsot/cli.py
mandsot/dataloader/__init__.py
mandsot/eval/__init__.py
mandsot/features/__init__.py
mandsot/model/__init__.py
mandsot/pretrained/__init__.py
mandsot/pretrained/sot_best.pth
mandsot/train/__init__.py
mandsot-0.0.2.dist-info/licenses/LICENSE
mandsot-0.0.2.dist-info/METADATA
mandsot-0.0.2.dist-info/WHEEL
mandsot-0.0.2.dist-info/entry_points.txt
mandsot-0.0.2.dist-info/top_level.txt
mandsot-0.0.2.dist-info/RECORD
