Metadata-Version: 2.4
Name: mandsot
Version: 0.0.2
Summary: CNN network for speech onset time (SOT) detection of Mandarin speech
Home-page: https://github.com/RyanYuanSun/MandSOT-CNN
Author: Tai Yuan
Author-email: tai.yuan@stonybrook.edu
License: MIT License
Requires-Python: >3
License-File: LICENSE
Requires-Dist: torch
Requires-Dist: numpy
Requires-Dist: pandas
Requires-Dist: librosa
Requires-Dist: noisereduce
Requires-Dist: matplotlib
Requires-Dist: scikit-learn
Requires-Dist: tqdm
Requires-Dist: praat-parselmouth
Dynamic: author
Dynamic: author-email
Dynamic: description-content-type
Dynamic: home-page
Dynamic: license
Dynamic: license-file
Dynamic: requires-dist
Dynamic: requires-python
Dynamic: summary
